{
  "saveID": 176640,
  "id": 0,
  "usesRippersReason": false,
  "ripperReason": 6,
  "usesRippersStatus": false,
  "ripperStatus": 2,
  "riftsDisclaimer": false,
  "wealthDieCalculated": "d6",
  "toughnessModifiers": [],
  "wealthDieActive": false,
  "wealthDieValue": "d6",
  "wealthDieBonus": 0,
  "usesSanity": false,
  "scholarship": 0,
  "usesETUScholarship": false,
  "noPowerPoints": false,
  "unarmoredHero": false,
  "hideHumanRaceDisplay": false,
  "usesStrain": false,
  "strainMax": 8,
  "strainCurrent": 8,
  "wealthFormatted": "$16.14",
  "playerName": "Austin",
  "naturalIsHeavy": false,
  "naturalArmor": [],
  "raceGenderAndProfession": "Seasoned Male Human, Drifter",
  "playerCharacter": true,
  "createdDate": "2026-06-26T04:05:37.113Z",
  "updatedDate": "2026-06-26T04:05:37.113Z",
  "appVersion": "3.2.4b031506",
  "abilities": [
    {
      "name": "Blessed",
      "description": "Power Points: 15; Powers: Barrier (Savage Worlds: Adventure Edition p155), Holy Symbol (Deadlands - The Weird West p76), Protection (Savage Worlds: Adventure Edition p165-166)",
      "note": "",
      "positive": true,
      "from": "",
      "takenFrom": "Deadlands",
      "bookID": 97
    },
    {
      "name": "Sinnin’",
      "description": "Blessed who violate their core beliefs (see Sin on page 56) are forsaken by whatever forces of good grant them their powers. Minor sins give the character −2 to his Faith rolls for a week. Major sins rob him of all arcane powers for a week. Mortal sins cause the character to be forsaken until the penitent hero completes some great quest or task of atonement to regain his lost powers.",
      "note": "Arcane Background",
      "positive": true,
      "from": "Arcane Background",
      "takenFrom": "Deadlands p55",
      "bookID": 97
    },
    {
      "name": "Languages Known",
      "description": "English (native, d8)",
      "note": "Special Ability",
      "positive": true,
      "from": "Special Ability",
      "takenFrom": "",
      "bookID": 0
    }
  ],
  "abs": [
    {
      "id": 72,
      "hasPowerPointPool": true,
      "uuid": "b96902c1-9c04-400d-1ea3-d7c5ccbe30d8",
      "hasMegaPowerOptions": false,
      "name": "Blessed",
      "powersTotal": 2,
      "powerPointsMax": 15,
      "powerPointsCurrent": 15,
      "arcaneSkill": "Faith",
      "takenFrom": "Deadlands p.55",
      "bookID": 97,
      "powerPointsName": "Power Points",
      "powers": [
        {
          "id": 58,
          "uuid": "0d473e43-f800-4800-0193-48af0b352c16",
          "name": "Barrier",
          "aspectOnlyName": "Barrier",
          "customName": "",
          "powerPoints": "2",
          "range": "Smarts",
          "takenFrom": "Savage Worlds: Adventure Edition p155",
          "bookID": 9,
          "damage": "",
          "damageWithBrackets": "",
          "duration": "5",
          "innate": false,
          "summary": "Creates 10 yard long, 2 yard tall, Toughness 10 barrier. - ",
          "description": "Barrier creates a straight wall 5′′ (10 yards)\nlong and 1′′ (two yards) tall, of immobile\nmaterial that conforms to the surface it’s cast\nupon. Thickness varies depending on what\nthe wall is made of, but is usually a few inches.\nThe wall has a Hardness of 10, and may be\ndestroyed as any other object (see Breaking\nThings on page 98).\n\nWhen the spell expires or the wall is broken\nit crumbles to dust or dissipates. Trap­pings\nare never left behind.\n",
          "bookPowerName": "Barrier",
          "trappings": "",
          "rank": "seasoned",
          "skillModifier": 0,
          "arcaneSkillName": "Faith",
          "arcaneSkillRoll": "d4",
          "powerModifiers": [
            "DAMAGE (+1): The barrier causes 2d4 damage to anyone who contacts it.",
            "SHAPED (+2): The barrier forms a circle, square or other basic shape.",
            "SIZE (+1): The length and height of the barrier doubles.",
            "STRONG (+1): The wall is Toughness 12."
          ],
          "additionalTargets": [
            ""
          ],
          "megaPowerOptions": [
            "STALWART WALLS (+2): The barrier gains +12 MDC Armor.",
            ""
          ],
          "descriptionHTML": "<p>Barrier creates a straight wall 5′′ (10 yards) long and 1′′ (two yards) tall, of immobile material that conforms to the surface it’s cast upon. Thickness varies depending on what the wall is made of, but is usually a few inches. The wall has a Hardness of 10, and may be destroyed as any other object (see Breaking Things on page 98).</p> <p>When the spell expires or the wall is broken it crumbles to dust or dissipates. Trap­pings are never left behind.</p><h3>Modifiers</h3><ul><li><b>Damage (+1)</b>: The barrier causes 2d4 damage to anyone who contacts it.</li><li><b>Shaped (+2)</b>: The barrier forms a circle, square or other basic shape.</li><li><b>Size (+1)</b>: The length and height of the barrier doubles.</li><li><b>Strong (+1)</b>: The wall is Toughness 12.</li></ul><p><cite>Savage Worlds: Adventure Edition p.155</cite></p>",
          "customDescription": "",
          "originalName": "Barrier"
        },
        {
          "id": 210,
          "uuid": "799636af-2863-47f0-bd2e-0f693120b640",
          "name": "Holy Symbol",
          "aspectOnlyName": "Holy Symbol",
          "customName": "",
          "powerPoints": "3",
          "range": "Self",
          "takenFrom": "Deadlands - The Weird West p76",
          "bookID": 97,
          "damage": "",
          "damageWithBrackets": "",
          "duration": "5",
          "innate": false,
          "summary": "Supernatural evil cannot touch you unless Spirit roll as free action (-2 on raise), requires a holy symbol. - ",
          "description": "",
          "bookPowerName": "Holy Symbol",
          "trappings": "",
          "rank": "novice",
          "skillModifier": 0,
          "arcaneSkillName": "Faith",
          "arcaneSkillRoll": "d4",
          "powerModifiers": [
            "AREA EFFECT (+2/+3): For +2 points the power affects all allies within a Medium Blast Template centered on the caster. It does not prevent creatures from entering the area, only their attacks against those within it. For +3 points the area of effect is increased to a Large Blast Template.",
            "STRONG (+1): Spirit rolls by the creature are made at −2 (–4 with a raise)."
          ],
          "additionalTargets": [],
          "megaPowerOptions": [],
          "descriptionHTML": "<h3>Modifiers</h3><ul><li><b>Area Effect (+2/+3)</b>: For +2 points the power affects all allies within a Medium Blast Template centered on the caster. It does not prevent creatures from entering the area, only their attacks against those within it. For +3 points the area of effect is increased to a Large Blast Template.</li><li><b>Strong (+1)</b>: Spirit rolls by the creature are made at −2 (–4 with a raise).</li></ul><p><cite>Deadlands - The Weird West p.76</cite></p>",
          "customDescription": "",
          "originalName": "Holy Symbol"
        },
        {
          "id": 93,
          "uuid": "a50aaa01-2150-4add-2b12-17e532cb3913",
          "name": "Protection",
          "aspectOnlyName": "Protection",
          "customName": "",
          "powerPoints": "1",
          "range": "Smarts",
          "takenFrom": "Savage Worlds: Adventure Edition p165-166",
          "bookID": 9,
          "damage": "",
          "damageWithBrackets": "",
          "duration": "5",
          "innate": false,
          "summary": "Grants Armor +2 (Toughness, with a raise). - ",
          "description": "Protection creates a field of energy or armor\naround a character, giving him 2 points of\nArmor, or +4 with a raise.\n\nWhether the protection is visible or not\ndepends on the Trapping — this is entirely\nup to the caster.\n\nProtection stacks with all other armor, natural\nor worn, and is negated by AP as usual.\n",
          "bookPowerName": "Protection",
          "trappings": "",
          "rank": "novice",
          "skillModifier": 0,
          "arcaneSkillName": "Faith",
          "arcaneSkillRoll": "d4",
          "powerModifiers": [
            "ADDITIONAL RECIPIENTS (+1): The power may affect additional targets at a cost of 1 Power Point each.",
            "MORE ARMOR (+1): Success grants 4 points of Armor (+6 with a raise).",
            "TOUGHNESS (+1): Protection provides Toughness instead of Armor and is not affected by AP (magical or otherwise). This means it stacks with natural or worn armor."
          ],
          "additionalTargets": [
            ""
          ],
          "megaPowerOptions": [
            "GREATER PROTECTION (+3): Protection provides 6 points of MDC Armor (+8 with a raise), which stacks with all other armor, natural or worn. May be combined with the Toughness Power Modifier, but not More Armor.",
            ""
          ],
          "descriptionHTML": "<p>Protection creates a field of energy or armor around a character, giving him 2 points of Armor, or +4 with a raise.</p> <p>Whether the protection is visible or not depends on the Trapping — this is entirely up to the caster.</p> <p>Protection stacks with all other armor, natural or worn, and is negated by AP as usual.</p><h3>Modifiers</h3><ul><li><b>Additional Recipients (+1)</b>: The power may affect additional targets at a cost of 1 Power Point each.</li><li><b>More Armor (+1)</b>: Success grants 4 points of Armor (+6 with a raise).</li><li><b>Toughness (+1)</b>: Protection provides Toughness instead of Armor and is not affected by AP (magical or otherwise). This means it stacks with natural or worn armor.</li></ul><p><cite>Savage Worlds: Adventure Edition p.165-166</cite></p>",
          "customDescription": "",
          "originalName": "Protection"
        }
      ]
    }
  ],
  "advances": [
    {
      "name": "Raise Attribute: Agility",
      "number": 1,
      "description": "Raise Attribute: Agility"
    },
    {
      "name": "Raise Skills: Fighting/Faith",
      "number": 2,
      "description": "Raise Skills: Fighting/Faith"
    },
    {
      "name": "Raise Skill: Survival",
      "number": 3,
      "description": "Raise Skill: Survival"
    },
    {
      "name": "Edge: Arcane Background (Blessed)",
      "number": 4,
      "description": "Edge: Arcane Background (Blessed)"
    }
  ],
  "advancesCount": 4,
  "age": "61",
  "armor": [
    {
      "id": 0,
      "uuid": "",
      "name": "(Unarmored)",
      "weight": 0,
      "quantity": 1,
      "armor": 0,
      "coversFace": true,
      "coversHead": true,
      "coversTorso": true,
      "coversLegs": true,
      "coversArms": true,
      "notes": "",
      "takenFrom": "",
      "bookID": 0,
      "descriptionHTML": "",
      "bookPublisher": "",
      "bookPublished": "",
      "bookName": "",
      "isShield": false,
      "equipped": false,
      "cost": 0,
      "costBuy": 0,
      "minStr": "",
      "equippedToughness": "6",
      "equippedStrength": "d6",
      "heavyArmor": false
    },
    {
      "id": 0,
      "uuid": "7d37720b-e95f-4089-2c83-3fc4ab976e02",
      "isShield": false,
      "name": "Armored hat (light) (cheap)",
      "weight": 2,
      "quantity": 1,
      "descriptionHTML": "<p><cite>Custom p.35</cite></p>",
      "armor": 1,
      "bookName": "Custom",
      "bookPublisher": "Custom",
      "bookPublished": "Custom",
      "coversFace": false,
      "coversHead": true,
      "coversTorso": false,
      "coversLegs": false,
      "coversArms": false,
      "notes": "",
      "takenFrom": "Deadlands p.35",
      "bookID": 97,
      "equipped": true,
      "cost": 20,
      "costBuy": 40,
      "minStr": "d4",
      "equippedToughness": "7 (1)",
      "equippedStrength": "d6",
      "heavyArmor": false
    },
    {
      "id": 0,
      "uuid": "7ba8d5ed-f45f-4776-261e-942d62d4e466",
      "isShield": false,
      "name": "Chaps (cheap)",
      "weight": 6,
      "quantity": 1,
      "descriptionHTML": "<p><cite>Custom p.26</cite></p>",
      "armor": 1,
      "bookName": "Custom",
      "bookPublisher": "Custom",
      "bookPublished": "Custom",
      "coversFace": false,
      "coversHead": false,
      "coversTorso": false,
      "coversLegs": true,
      "coversArms": false,
      "notes": "",
      "takenFrom": "Deadlands p.26",
      "bookID": 97,
      "equipped": true,
      "cost": 2,
      "costBuy": 4,
      "minStr": "d4",
      "equippedToughness": "7 (1)",
      "equippedStrength": "d6",
      "heavyArmor": false
    },
    {
      "id": 306,
      "uuid": "5444178c-bd33-4324-1ef8-c87cf5749a2e",
      "isShield": false,
      "name": "Native Armor",
      "weight": 3,
      "quantity": 1,
      "descriptionHTML": "<p><cite>Deadlands - The Weird West p.26</cite></p>",
      "armor": 1,
      "bookName": "Deadlands - The Weird West",
      "bookPublisher": "Pinnacle Entertainement Group",
      "bookPublished": "2020",
      "coversFace": false,
      "coversHead": false,
      "coversTorso": true,
      "coversLegs": false,
      "coversArms": false,
      "notes": "",
      "takenFrom": "Deadlands p.26",
      "bookID": 97,
      "equipped": true,
      "cost": 2,
      "costBuy": 2,
      "minStr": "d4",
      "equippedToughness": "7 (1)",
      "equippedStrength": "d6",
      "heavyArmor": false
    }
  ],
  "armorValue": 1,
  "attributes": [
    {
      "name": "agility",
      "label": "Agility ",
      "value": "d8",
      "mod": -2,
      "dieValue": 8
    },
    {
      "name": "smarts",
      "label": "Smarts ",
      "value": "d6",
      "mod": 0,
      "dieValue": 6
    },
    {
      "name": "spirit",
      "label": "Spirit ",
      "value": "d8",
      "mod": 0,
      "dieValue": 8
    },
    {
      "name": "strength",
      "label": "Strength ",
      "value": "d6",
      "mod": -1,
      "dieValue": 6
    },
    {
      "name": "vigor",
      "label": "Vigor ",
      "value": "d8",
      "mod": -1,
      "dieValue": 8
    }
  ],
  "background": "Dusty McCaw was raised on his parents' ranch outside a tight-knit Mormon settlement in Deseret. From a young age he had a quiet curiosity about things the sermons did not explain. He asked travelers questions, kept strange pamphlets, and experimented with charms and remedies that sat somewhere between folk medicine and forbidden study. Most folks tolerated it as harmless eccentricity until the plague hit. \n\nThe Plague began with Dusty's cattle. When the plague spread to neighboring ranches, whispers turned to accusation. By the time townsfolk began falling ill, fear needed a scapegoat, and Dusty's curiosity made him an easy target. Leadership did not drag him out in chains; they told him, clearly and publicly, that he and his family must leave for the good of the community. No trial was had, and no proof presented.\n\nThe fever followed them into exile. He watched his wife and children die one by one, scouring every scrap of occult knowledge he possessed in a desperate attempt to call them back. None of them answered. His last companion was his horse, the only living thing that remained beside him, and when it too fell to the sickness and died at his side, something in Dusty broke clean. He gave up on raising the dead that day. From then on, he turned all his study toward healing and prevention, vowing that if death came again, he would meet it before it could claim another soul.",
  "bennies": 2,
  "benniesMax": 2,
  "bookName": "Custom",
  "bookID": 0,
  "bookPrimary": false,
  "bookCore": false,
  "bookPublished": "",
  "bookPublisher": "",
  "charisma": 0,
  "cyberware": [],
  "description": "Dusty McCaw is sixty-one years old and looks every day of it, though not in a fragile way. He is lean rather than frail, with the kind of wiry strength that comes from decades of fence mending, saddle lifting, and long days in the sun. His shoulders are slightly rounded from years in the saddle. One knee stiffens when the weather turns cold, and he stands up slow, but once he's moving, he moves steadily.\n\nHis face is narrow and weather-cut, deep lines carved around the mouth and eyes. His beard is more gray than brown now, trimmed short when he has the chance, left uneven when he does not. His hands are calloused and cracked, permanently stained with dust and oil. His clothes are clean when possible but worn thin: an old hat reshaped more times than it should have survived, a faded coat with careful patches, boots that have been resoled twice.",
  "edges": [
    {
      "id": 951,
      "customDescription": "",
      "name": "Arcane Background (Blessed)",
      "description": "Can call upon the power of their deity for aid.",
      "note": "Advance",
      "takenFrom": "Deadlands p17",
      "bookID": 97,
      "isHidden": false,
      "descriptionHTML": "<p>Can call upon the power of their deity for aid.</p><p><cite>Deadlands - The Weird West p.17</cite></p>"
    },
    {
      "id": 281,
      "customDescription": "",
      "name": "Healer",
      "description": "+2 to Healing rolls, magical or otherwise.",
      "note": "Selected",
      "takenFrom": "SWADE p52",
      "bookID": 9,
      "isHidden": false,
      "descriptionHTML": "<p>+2 to Healing rolls, magical or otherwise.</p><p><cite>Savage Worlds: Adventure Edition p.52</cite></p>"
    }
  ],
  "fatigue": 0,
  "fatigueMax": 2,
  "gear": [
    {
      "id": 0,
      "uuid": "a56e6cf6-2b5c-476b-8679-f5e0be3ea34c",
      "name": "Backpack (cheap)",
      "weight": 42,
      "quantity": 1,
      "contains": {
        "gear": [
          {
            "id": 928,
            "uuid": "d39f51cd-2927-467c-a100-a4c9c4b68f3d",
            "name": "Bedroll",
            "weight": 10,
            "quantity": 1,
            "contains": {
              "gear": [],
              "weapons": [],
              "armor": [],
              "shields": []
            },
            "notes": "",
            "summary": "",
            "descriptionHTML": "<p><cite>Deadlands - The Weird West p.27</cite></p>",
            "container": false,
            "bookPublished": "2020",
            "bookPublisher": "Pinnacle Entertainement Group",
            "equipped": false,
            "cost": 4,
            "takenFrom": "Deadlands p.27",
            "bookID": 97,
            "costBuy": 4
          },
          {
            "id": 1313,
            "uuid": "b6297407-659f-4706-afe7-df0cfccc70a6",
            "name": "Doctor's Bag",
            "weight": 6,
            "quantity": 1,
            "contains": {
              "gear": [],
              "weapons": [],
              "armor": [],
              "shields": []
            },
            "notes": "",
            "summary": "",
            "descriptionHTML": "<p><cite>Deadlands - The Weird West p.27</cite></p>",
            "container": false,
            "bookPublished": "2020",
            "bookPublisher": "Pinnacle Entertainement Group",
            "equipped": false,
            "cost": 10,
            "takenFrom": "Deadlands p.27",
            "bookID": 97,
            "costBuy": 10
          },
          {
            "id": 943,
            "uuid": "f0b6d4b3-91ab-4279-2de9-6432312ab287",
            "name": "Lantern",
            "weight": 4,
            "quantity": 1,
            "contains": {
              "gear": [],
              "weapons": [],
              "armor": [],
              "shields": []
            },
            "notes": "Provides light in a 4” radius for three hours per pint of oil. If it’s dropped there’s a 50% chance the lantern breaks, and a 1-in-6 chance it sets normal combustibles alight.  ",
            "summary": "Provides light in a 4” radius for three hours per pint of oil. If it’s dropped there’s a 50% chance the lantern breaks, and a 1-in-6 chance it sets normal combustibles alight.  ",
            "descriptionHTML": "<p><cite>Deadlands - The Weird West p.27</cite></p>",
            "container": false,
            "bookPublished": "2020",
            "bookPublisher": "Pinnacle Entertainement Group",
            "equipped": false,
            "cost": 2.5,
            "takenFrom": "Deadlands p.27",
            "bookID": 97,
            "costBuy": 2.5
          },
          {
            "id": 924,
            "uuid": "d516b589-5312-4564-b7ee-0a386ee50f65",
            "name": "Trail Rations (per day)",
            "weight": 12,
            "quantity": 4,
            "contains": {
              "gear": [],
              "weapons": [],
              "armor": [],
              "shields": []
            },
            "notes": "",
            "summary": "",
            "descriptionHTML": "<p><cite>Deadlands - The Weird West p.26</cite></p>",
            "container": false,
            "bookPublished": "2020",
            "bookPublisher": "Pinnacle Entertainement Group",
            "equipped": false,
            "cost": 0.125,
            "takenFrom": "Deadlands p.26",
            "bookID": 97,
            "costBuy": 0.125
          },
          {
            "id": 930,
            "uuid": "b04f4fe4-3a19-4031-105f-05812d7ace1b",
            "name": "Canteen",
            "weight": 5,
            "quantity": 1,
            "contains": {
              "gear": [],
              "weapons": [],
              "armor": [],
              "shields": []
            },
            "notes": "",
            "summary": "",
            "descriptionHTML": "<p><cite>Deadlands - The Weird West p.27</cite></p>",
            "container": false,
            "bookPublished": "2020",
            "bookPublisher": "Pinnacle Entertainement Group",
            "equipped": false,
            "cost": 1,
            "takenFrom": "Deadlands p.27",
            "bookID": 97,
            "costBuy": 1
          },
          {
            "id": 946,
            "uuid": "49be0ccf-ce94-4d56-2f8e-86af80b3a5f5",
            "name": "Matches (box 100)",
            "weight": 0.25,
            "quantity": 1,
            "contains": {
              "gear": [],
              "weapons": [],
              "armor": [],
              "shields": []
            },
            "notes": "",
            "summary": "",
            "descriptionHTML": "<p><cite>Deadlands - The Weird West p.27</cite></p>",
            "container": false,
            "bookPublished": "2020",
            "bookPublisher": "Pinnacle Entertainement Group",
            "equipped": false,
            "cost": 0.5,
            "takenFrom": "Deadlands p.27",
            "bookID": 97,
            "costBuy": 0.5
          },
          {
            "id": 998,
            "uuid": "c4bb0918-469e-4c39-8bc1-f6069f12d0e4",
            "name": "Restoration elixir",
            "weight": 0,
            "quantity": 1,
            "contains": {
              "gear": [],
              "weapons": [],
              "armor": [],
              "shields": []
            },
            "notes": "The drinker recovers all Fatigue levels.",
            "summary": "The drinker recovers all Fatigue levels.",
            "descriptionHTML": "<p><cite>Deadlands - The Weird West p.34</cite></p>",
            "container": false,
            "bookPublished": "2020",
            "bookPublisher": "Pinnacle Entertainement Group",
            "equipped": false,
            "cost": 100,
            "takenFrom": "Deadlands p.34",
            "bookID": 97,
            "costBuy": 100
          },
          {
            "id": 955,
            "uuid": "c3d4c521-458f-492c-a10b-b908e6155e49",
            "name": "Tobacco, smoking (pouch)",
            "weight": 1,
            "quantity": 1,
            "contains": {
              "gear": [],
              "weapons": [],
              "armor": [],
              "shields": []
            },
            "notes": "",
            "summary": "",
            "descriptionHTML": "<p><cite>Deadlands - The Weird West p.27</cite></p>",
            "container": false,
            "bookPublished": "2020",
            "bookPublisher": "Pinnacle Entertainement Group",
            "equipped": false,
            "cost": 0.5,
            "takenFrom": "Deadlands p.27",
            "bookID": 97,
            "costBuy": 0.5
          },
          {
            "id": 949,
            "uuid": "8a67fef2-3621-45a4-19e0-5a3707097c6d",
            "name": "Pipe",
            "weight": 0.75,
            "quantity": 1,
            "contains": {
              "gear": [],
              "weapons": [],
              "armor": [],
              "shields": []
            },
            "notes": "",
            "summary": "",
            "descriptionHTML": "<p><cite>Deadlands - The Weird West p.27</cite></p>",
            "container": false,
            "bookPublished": "2020",
            "bookPublisher": "Pinnacle Entertainement Group",
            "equipped": false,
            "cost": 2,
            "takenFrom": "Deadlands p.27",
            "bookID": 97,
            "costBuy": 2
          }
        ],
        "weapons": [],
        "armor": [],
        "shields": []
      },
      "notes": "",
      "summary": "",
      "descriptionHTML": "<p><cite>Custom p.27</cite></p>",
      "container": true,
      "bookPublished": "Custom",
      "bookPublisher": "Custom",
      "equipped": true,
      "cost": 1,
      "takenFrom": "Deadlands p.27",
      "bookID": 97,
      "costBuy": 2
    },
    {
      "id": 0,
      "uuid": "23aa676c-de7d-479d-b748-77aa1fcb030a",
      "name": "Boots (cheap)",
      "weight": 4,
      "quantity": 1,
      "contains": {
        "gear": [],
        "weapons": [],
        "armor": [],
        "shields": []
      },
      "notes": "",
      "summary": "",
      "descriptionHTML": "<p><cite>Custom p.26</cite></p>",
      "container": false,
      "bookPublished": "Custom",
      "bookPublisher": "Custom",
      "equipped": true,
      "cost": 4,
      "takenFrom": "Deadlands p.26",
      "bookID": 97,
      "costBuy": 8
    },
    {
      "id": 963,
      "uuid": "c3df0ac4-29b9-4608-86bd-c5f6e40f192f",
      "name": "Holster",
      "weight": 1,
      "quantity": 1,
      "contains": {
        "gear": [],
        "weapons": [],
        "armor": [],
        "shields": []
      },
      "notes": "",
      "summary": "",
      "descriptionHTML": "<p><cite>Deadlands - The Weird West p.27</cite></p>",
      "container": false,
      "bookPublished": "2020",
      "bookPublisher": "Pinnacle Entertainement Group",
      "equipped": true,
      "cost": 3,
      "takenFrom": "Deadlands p.27",
      "bookID": 97,
      "costBuy": 3
    },
    {
      "id": 979,
      "uuid": "9c541ac8-0704-42fa-92b5-a7d5b6480559",
      "name": "Pistol Ammunition (Large, .40-.50 caliber)",
      "weight": 4.1000000000000005,
      "quantity": 41,
      "contains": {
        "gear": [],
        "weapons": [],
        "armor": [],
        "shields": []
      },
      "notes": ".40-.50 caliber",
      "summary": ".40-.50 caliber",
      "descriptionHTML": "<p><cite>Deadlands - The Weird West p.28</cite></p>",
      "container": false,
      "bookPublished": "2020",
      "bookPublisher": "Pinnacle Entertainement Group",
      "equipped": false,
      "cost": 0.0014634146341463415,
      "takenFrom": "Deadlands p.28",
      "bookID": 97,
      "costBuy": 0.0014634146341463415
    },
    {
      "id": 980,
      "uuid": "6b5f0e1b-e257-4404-ac99-63c1cc293b68",
      "name": "Rifle Ammunition (Small, .38-.44 caliber)",
      "weight": 1.2,
      "quantity": 10,
      "contains": {
        "gear": [],
        "weapons": [],
        "armor": [],
        "shields": []
      },
      "notes": ".38-.44 caliber",
      "summary": ".38-.44 caliber",
      "descriptionHTML": "<p><cite>Deadlands - The Weird West p.28</cite></p>",
      "container": false,
      "bookPublished": "2020",
      "bookPublisher": "Pinnacle Entertainement Group",
      "equipped": false,
      "cost": 0.008,
      "takenFrom": "Deadlands p.28",
      "bookID": 97,
      "costBuy": 0.008
    },
    {
      "id": 0,
      "uuid": "7d732bcc-f0e1-46fd-9f6a-cada512f5dff",
      "name": "Shirt/blouse, work (cheap)",
      "weight": 1,
      "quantity": 1,
      "contains": {
        "gear": [],
        "weapons": [],
        "armor": [],
        "shields": []
      },
      "notes": "",
      "summary": "",
      "descriptionHTML": "<p><cite>Custom p.26</cite></p>",
      "container": false,
      "bookPublished": "Custom",
      "bookPublisher": "Custom",
      "equipped": true,
      "cost": 0.5,
      "takenFrom": "Deadlands p.26",
      "bookID": 97,
      "costBuy": 1
    },
    {
      "id": 0,
      "uuid": "315cf0ff-25f6-46fe-3f5d-654d018ad379",
      "name": "Trousers/skirt (cheap)",
      "weight": 2,
      "quantity": 1,
      "contains": {
        "gear": [],
        "weapons": [],
        "armor": [],
        "shields": []
      },
      "notes": "",
      "summary": "",
      "descriptionHTML": "<p><cite>Custom p.26</cite></p>",
      "container": false,
      "bookPublished": "Custom",
      "bookPublisher": "Custom",
      "equipped": true,
      "cost": 1,
      "takenFrom": "Deadlands p.26",
      "bookID": 97,
      "costBuy": 2
    }
  ],
  "gender": "Male",
  "heavyArmor": false,
  "hindrances": [
    {
      "id": 106,
      "name": "Bad Luck (major)",
      "customDescription": "",
      "description": "The characters starts with one less Benny per session.",
      "note": "Selected",
      "major": true,
      "takenFrom": "SWADE p22",
      "bookID": 9,
      "isHidden": false,
      "descriptionHTML": "<p>The characters starts with one less Benny per session.</p><p><cite>Savage Worlds: Adventure Edition p.22</cite></p>"
    },
    {
      "id": 379,
      "name": "Cursed (major)",
      "customDescription": "",
      "description": "The GM starts with an extra Benny!",
      "note": "Selected",
      "major": true,
      "takenFrom": "Deadlands p15",
      "bookID": 97,
      "isHidden": false,
      "descriptionHTML": "<p>The GM starts with an extra Benny!</p><p><cite>Deadlands - The Weird West p.15</cite></p>"
    },
    {
      "id": 120,
      "name": "Elderly (major)",
      "customDescription": "",
      "description": "Pace –1, Agility, Strength, and Vigor rolls –1, but hero gets 5 extra skill points.",
      "note": "Selected",
      "major": true,
      "takenFrom": "SWADE p24",
      "bookID": 9,
      "isHidden": false,
      "descriptionHTML": "<p>Pace –1, Agility, Strength, and Vigor rolls –1, but hero gets 5 extra skill points.</p><p><cite>Savage Worlds: Adventure Edition p.24</cite></p>"
    }
  ],
  "iconicFramework": "",
  "settingImage": "/shares/data/setting-15.png",
  "image": "https://savaged.us/data-images/users/33145-session-character.webp?v=1782446737.113",
  "imageToken": "",
  "alliedExtras": [],
  "journal": [
    {
      "date": "2026-02-25T12:28:14.000Z",
      "title": "2026-02-25",
      "text": "We rode out to the old homestead where the office is meant to stand. Travis Morcy, Doc Brown, Jolene Reeves, Eleanor Finch, myself, and a quiet fellow whose name I never did catch. Place looked worn down but still upright, like it was waiting to see if we meant to stay.\n\nTravis wasted no time. Walked straight up, slipped through a window like he owned the place, and before I’d even finished counting my breath there were four shots echoing through the boards. A caterwaul came tearing out the back, bleeding and furious, smashing shutters clean off as it fled. It ran hard into the dark. Wounded, but not dead. Things like that don’t quit easy.\n\nDoc put the window right again, good work there. Then he tried his hand at building a toaster of all things. The window holds. The toaster does not. He and Travis took turns cranking at it, but neither could spin the shaft quick enough to warm the coils. I reckon some things are better left to steady fires than spinning gears.\n\nEleanor found a barn close by and settled her horse, Sassifrass, inside. Doc lined the entrance with bear traps in case that caterwaul decides it’s got unfinished business. Smart precaution. Wounded beasts remember.\n\nAs for me, I laid my bedroll beneath a tree just off the house. No sense crowding the others. I’ve slept under worse skies than this one. If that creature comes back in the night, I expect I’ll hear it before most."
    }
  ],
  "languages": [
    {
      "name": "English",
      "attribute": "smarts",
      "value": "d8",
      "dieValue": 8,
      "mod": 0,
      "isCore": false,
      "bookID": 9
    }
  ],
  "load": 86.3,
  "loadLimit": 41,
  "loadLimitBase": 41,
  "loadLimitModifier": 0,
  "name": "Dusty McCaw",
  "paceBase": 6,
  "paceMod": -2,
  "paceTotal": 4,
  "parryBase": 4,
  "parryMod": 0,
  "parryTotal": 4,
  "parryShield": 0,
  "parryHR": "4",
  "professionOrTitle": "Drifter",
  "race": "Human",
  "rank": 1,
  "rankName": "Seasoned",
  "runningDie": "d6",
  "sanity": 6,
  "savagedUsShareURL": "",
  "shields": [],
  "size": 0,
  "sizeLabel": "0 (Normal)",
  "skills": [
    {
      "name": "(Unskilled)",
      "attribute": "",
      "value": "d4-2",
      "dieValue": 4,
      "mod": -2,
      "isCore": false,
      "bookID": 0
    },
    {
      "name": "Athletics",
      "attribute": "agility",
      "value": "d4-1",
      "dieValue": 4,
      "mod": 0,
      "isCore": true,
      "bookID": 9
    },
    {
      "name": "Common Knowledge",
      "attribute": "smarts",
      "value": "d4",
      "dieValue": 4,
      "mod": 0,
      "isCore": true,
      "bookID": 9
    },
    {
      "name": "Faith",
      "attribute": "spirit",
      "value": "d4",
      "dieValue": 4,
      "mod": 0,
      "isCore": false,
      "bookID": 9
    },
    {
      "name": "Fighting",
      "attribute": "agility",
      "value": "d4-1",
      "dieValue": 4,
      "mod": 0,
      "isCore": false,
      "bookID": 9
    },
    {
      "name": "Healing",
      "attribute": "smarts",
      "value": "d8+2",
      "dieValue": 8,
      "mod": 2,
      "isCore": false,
      "bookID": 9
    },
    {
      "name": "Language (English)",
      "attribute": "smarts",
      "value": "d8",
      "dieValue": 8,
      "mod": 0,
      "isCore": false,
      "bookID": 9
    },
    {
      "name": "Notice",
      "attribute": "smarts",
      "value": "d8",
      "dieValue": 8,
      "mod": 0,
      "isCore": true,
      "bookID": 9
    },
    {
      "name": "Occult",
      "attribute": "smarts",
      "value": "d6",
      "dieValue": 6,
      "mod": 0,
      "isCore": false,
      "bookID": 9
    },
    {
      "name": "Persuasion",
      "attribute": "spirit",
      "value": "d4",
      "dieValue": 4,
      "mod": 0,
      "isCore": true,
      "bookID": 9
    },
    {
      "name": "Riding",
      "attribute": "agility",
      "value": "d6-1",
      "dieValue": 6,
      "mod": 0,
      "isCore": false,
      "bookID": 9
    },
    {
      "name": "Shooting",
      "attribute": "agility",
      "value": "d8-1",
      "dieValue": 8,
      "mod": 0,
      "isCore": false,
      "bookID": 9
    },
    {
      "name": "Stealth",
      "attribute": "agility",
      "value": "d4-1",
      "dieValue": 4,
      "mod": 0,
      "isCore": true,
      "bookID": 9
    },
    {
      "name": "Survival",
      "attribute": "smarts",
      "value": "d8",
      "dieValue": 8,
      "mod": 0,
      "isCore": false,
      "bookID": 9
    }
  ],
  "allSkills": [
    {
      "name": "(Unskilled)",
      "attribute": "",
      "value": "d4-2",
      "dieValue": 4,
      "mod": -2,
      "isCore": false,
      "bookID": 0
    },
    {
      "name": "Academics",
      "attribute": "smarts",
      "value": "-",
      "dieValue": 0,
      "mod": 0,
      "isCore": false,
      "bookID": 9
    },
    {
      "name": "Athletics",
      "attribute": "agility",
      "value": "d4-1",
      "dieValue": 4,
      "mod": 0,
      "isCore": true,
      "bookID": 9
    },
    {
      "name": "Battle",
      "attribute": "smarts",
      "value": "-",
      "dieValue": 0,
      "mod": 0,
      "isCore": false,
      "bookID": 9
    },
    {
      "name": "Boating",
      "attribute": "agility",
      "value": "--1",
      "dieValue": 0,
      "mod": 0,
      "isCore": false,
      "bookID": 9
    },
    {
      "name": "Common Knowledge",
      "attribute": "smarts",
      "value": "d4",
      "dieValue": 4,
      "mod": 0,
      "isCore": true,
      "bookID": 9
    },
    {
      "name": "Driving",
      "attribute": "agility",
      "value": "--1",
      "dieValue": 0,
      "mod": 0,
      "isCore": false,
      "bookID": 9
    },
    {
      "name": "Faith",
      "attribute": "spirit",
      "value": "d4",
      "dieValue": 4,
      "mod": 0,
      "isCore": false,
      "bookID": 9
    },
    {
      "name": "Fighting",
      "attribute": "agility",
      "value": "d4-1",
      "dieValue": 4,
      "mod": 0,
      "isCore": false,
      "bookID": 9
    },
    {
      "name": "Focus",
      "attribute": "spirit",
      "value": "-",
      "dieValue": 0,
      "mod": 0,
      "isCore": false,
      "bookID": 9
    },
    {
      "name": "Gambling",
      "attribute": "smarts",
      "value": "-",
      "dieValue": 0,
      "mod": 0,
      "isCore": false,
      "bookID": 9
    },
    {
      "name": "Healing",
      "attribute": "smarts",
      "value": "d8+2",
      "dieValue": 8,
      "mod": 2,
      "isCore": false,
      "bookID": 9
    },
    {
      "name": "Intimidation",
      "attribute": "spirit",
      "value": "-",
      "dieValue": 0,
      "mod": 0,
      "isCore": false,
      "bookID": 9
    },
    {
      "name": "Language (English)",
      "attribute": "smarts",
      "value": "d8",
      "dieValue": 8,
      "mod": 0,
      "isCore": false,
      "bookID": 9
    },
    {
      "name": "Notice",
      "attribute": "smarts",
      "value": "d8",
      "dieValue": 8,
      "mod": 0,
      "isCore": true,
      "bookID": 9
    },
    {
      "name": "Occult",
      "attribute": "smarts",
      "value": "d6",
      "dieValue": 6,
      "mod": 0,
      "isCore": false,
      "bookID": 9
    },
    {
      "name": "Performance",
      "attribute": "spirit",
      "value": "-",
      "dieValue": 0,
      "mod": 0,
      "isCore": false,
      "bookID": 9
    },
    {
      "name": "Persuasion",
      "attribute": "spirit",
      "value": "d4",
      "dieValue": 4,
      "mod": 0,
      "isCore": true,
      "bookID": 9
    },
    {
      "name": "Piloting",
      "attribute": "agility",
      "value": "--1",
      "dieValue": 0,
      "mod": 0,
      "isCore": false,
      "bookID": 9
    },
    {
      "name": "Psionics",
      "attribute": "smarts",
      "value": "-",
      "dieValue": 0,
      "mod": 0,
      "isCore": false,
      "bookID": 9
    },
    {
      "name": "Repair",
      "attribute": "smarts",
      "value": "-",
      "dieValue": 0,
      "mod": 0,
      "isCore": false,
      "bookID": 9
    },
    {
      "name": "Research",
      "attribute": "smarts",
      "value": "-",
      "dieValue": 0,
      "mod": 0,
      "isCore": false,
      "bookID": 9
    },
    {
      "name": "Riding",
      "attribute": "agility",
      "value": "d6-1",
      "dieValue": 6,
      "mod": 0,
      "isCore": false,
      "bookID": 9
    },
    {
      "name": "Science",
      "attribute": "smarts",
      "value": "-",
      "dieValue": 0,
      "mod": 0,
      "isCore": false,
      "bookID": 9
    },
    {
      "name": "Shooting",
      "attribute": "agility",
      "value": "d8-1",
      "dieValue": 8,
      "mod": 0,
      "isCore": false,
      "bookID": 9
    },
    {
      "name": "Spellcasting",
      "attribute": "smarts",
      "value": "-",
      "dieValue": 0,
      "mod": 0,
      "isCore": false,
      "bookID": 9
    },
    {
      "name": "Stealth",
      "attribute": "agility",
      "value": "d4-1",
      "dieValue": 4,
      "mod": 0,
      "isCore": true,
      "bookID": 9
    },
    {
      "name": "Survival",
      "attribute": "smarts",
      "value": "d8",
      "dieValue": 8,
      "mod": 0,
      "isCore": false,
      "bookID": 9
    },
    {
      "name": "Taunt",
      "attribute": "smarts",
      "value": "-",
      "dieValue": 0,
      "mod": 0,
      "isCore": false,
      "bookID": 9
    },
    {
      "name": "Thievery",
      "attribute": "agility",
      "value": "--1",
      "dieValue": 0,
      "mod": 0,
      "isCore": false,
      "bookID": 9
    },
    {
      "name": "Trade",
      "attribute": "smarts",
      "value": "-",
      "dieValue": 0,
      "mod": 0,
      "isCore": false,
      "bookID": 97
    },
    {
      "name": "Weird Science",
      "attribute": "smarts",
      "value": "-",
      "dieValue": 0,
      "mod": 0,
      "isCore": false,
      "bookID": 9
    }
  ],
  "swade": true,
  "toughnessBase": 6,
  "toughnessMod": 0,
  "toughnessTotal": 7,
  "toughnessTotalNoArmor": 6,
  "toughnessAsRead": "7 (1)",
  "toughnessAsReadNoHeavy": "7 (1)",
  "toughnessHeavyLabel": "",
  "usesCharisma": false,
  "usesXP": false,
  "uuid": "8a418507-68ab-49de-9f18-98a1cd8686e0",
  "vehicles": [],
  "wealth": 18.12,
  "weapons": [
    {
      "id": 0,
      "uuid": "83d3306e-da0b-4866-3604-9a66e3c9a0cd",
      "name": "Unarmed",
      "weight": 0,
      "range": "Melee",
      "damage": "Str",
      "equippedAs": "",
      "descriptionHTML": "<p><cite>Custom</cite></p>",
      "damageWithBrackets": "Str[d6]",
      "rof": 0,
      "shots": 0,
      "ap": 0,
      "bookName": "Custom",
      "bookPublisher": "Custom",
      "bookPublished": "Custom",
      "notes": "Innate Attack",
      "takenFrom": "Custom",
      "thrown": false,
      "quantity": 1,
      "reach": 0,
      "innate": true,
      "damageDiceBase": "",
      "damageDiceBasePlus": 0,
      "equipped": false,
      "cost": 0,
      "costBuy": 0,
      "minStr": "",
      "profiles": [
        {
          "name": "",
          "damage": "Str",
          "damageWithBrackets": "Str[d6]",
          "damage_original": "",
          "parry_modifier": 0,
          "range": "Melee",
          "reach": 0,
          "requires_2_hands": false,
          "rof": 0,
          "shots": 0,
          "heavy_weapon": false,
          "melee_only": false,
          "notes": "Innate Attack",
          "currentShots": 0,
          "additionalDamage": "",
          "damageDiceBasePlus": 0,
          "damageDiceBase": "1d6",
          "toHitMod": 0,
          "is_shield": false,
          "thrown_weapon": false,
          "usable_in_melee": false,
          "counts_as_innate": false,
          "add_strength_to_damage": true,
          "ap": 0,
          "ap_vs_rigid_armor_only": 0,
          "vtt_only": false,
          "skillName": "Shooting",
          "skillValue": "d8-1"
        }
      ],
      "bookID": 0,
      "activeProfile": 0
    },
    {
      "id": 1046,
      "uuid": "3fb64572-daf5-4d9c-3aa7-bffe6636b542",
      "name": "Colt Army (.44)",
      "weight": 2,
      "range": "12/24/48",
      "damage": "2d6+1",
      "equippedAs": "",
      "descriptionHTML": "<p><cite>Deadlands - The Weird West p.30</cite></p>",
      "damageWithBrackets": "2d6+1",
      "rof": 1,
      "shots": 6,
      "ap": 1,
      "bookName": "Deadlands - The Weird West",
      "bookPublisher": "Pinnacle Entertainement Group",
      "bookPublished": "2020",
      "notes": "",
      "takenFrom": "Deadlands p.30",
      "thrown": false,
      "quantity": 1,
      "reach": 0,
      "innate": false,
      "damageDiceBase": "2d6",
      "damageDiceBasePlus": 1,
      "equipped": false,
      "cost": 12,
      "costBuy": 12,
      "minStr": "d4",
      "profiles": [
        {
          "ap": 1,
          "rof": 1,
          "name": "",
          "notes": "",
          "range": "12/24/48",
          "reach": 0,
          "shots": 6,
          "damage": "2d6+1",
          "toHitMod": 0,
          "vtt_only": false,
          "is_shield": false,
          "skillName": "Shooting",
          "melee_only": false,
          "skillValue": "d8-1",
          "currentShots": 0,
          "heavy_weapon": false,
          "thrown_weapon": false,
          "damageDiceBase": "2d6",
          "parry_modifier": 0,
          "damage_original": "2d6+1",
          "usable_in_melee": false,
          "counts_as_innate": false,
          "requires_2_hands": false,
          "damageDiceBasePlus": 1,
          "damageWithBrackets": "2d6+1",
          "add_strength_to_damage": false,
          "ap_vs_rigid_armor_only": 0
        }
      ],
      "bookID": 97,
      "activeProfile": 0
    },
    {
      "id": 1053,
      "uuid": "9c661db3-5ffb-4c6c-018a-c7bc70c523fb",
      "name": "Colt Frontier (.44-40)",
      "weight": 2,
      "range": "12/24/48",
      "damage": "2d6+1",
      "equippedAs": "",
      "descriptionHTML": "<p><cite>Deadlands - The Weird West p.30</cite></p>",
      "damageWithBrackets": "2d6+1",
      "rof": 1,
      "shots": 6,
      "ap": 1,
      "bookName": "Deadlands - The Weird West",
      "bookPublisher": "Pinnacle Entertainement Group",
      "bookPublished": "2020",
      "notes": "",
      "takenFrom": "Deadlands p.30",
      "thrown": false,
      "quantity": 2,
      "reach": 0,
      "innate": false,
      "damageDiceBase": "2d6",
      "damageDiceBasePlus": 1,
      "equipped": false,
      "cost": 7.5,
      "costBuy": 0.775,
      "minStr": "d4",
      "profiles": [
        {
          "ap": 1,
          "rof": 1,
          "name": "",
          "notes": "",
          "range": "12/24/48",
          "reach": 0,
          "shots": 6,
          "damage": "2d6+1",
          "toHitMod": 0,
          "vtt_only": false,
          "is_shield": false,
          "skillName": "Shooting",
          "melee_only": false,
          "skillValue": "d8-1",
          "currentShots": 0,
          "heavy_weapon": false,
          "thrown_weapon": false,
          "damageDiceBase": "2d6",
          "parry_modifier": 0,
          "damage_original": "2d6+1",
          "usable_in_melee": false,
          "counts_as_innate": false,
          "requires_2_hands": false,
          "damageDiceBasePlus": 1,
          "damageWithBrackets": "2d6+1",
          "add_strength_to_damage": false,
          "ap_vs_rigid_armor_only": 0
        }
      ],
      "bookID": 97,
      "activeProfile": 0
    },
    {
      "id": 1025,
      "uuid": "eb4eeb77-48bd-4087-1d65-ea120b049620",
      "name": "Knife",
      "weight": 1,
      "range": "Melee",
      "damage": "Str+d4",
      "equippedAs": "",
      "descriptionHTML": "<p><cite>Deadlands - The Weird West p.29</cite></p>",
      "damageWithBrackets": "Str[d6]+d4",
      "rof": 0,
      "shots": 0,
      "ap": 0,
      "bookName": "Deadlands - The Weird West",
      "bookPublisher": "Pinnacle Entertainement Group",
      "bookPublished": "2020",
      "notes": "",
      "takenFrom": "Deadlands p.29",
      "thrown": false,
      "quantity": 1,
      "reach": 0,
      "innate": false,
      "damageDiceBase": "1d4",
      "damageDiceBasePlus": 0,
      "equipped": false,
      "cost": 2,
      "costBuy": 2,
      "minStr": "d4",
      "profiles": [
        {
          "ap": 0,
          "rof": 0,
          "name": "",
          "notes": "",
          "range": "Melee",
          "reach": 0,
          "shots": 0,
          "damage": "Str+d4",
          "toHitMod": 0,
          "vtt_only": false,
          "is_shield": false,
          "skillName": "Fighting",
          "melee_only": true,
          "skillValue": "d4-1",
          "currentShots": 0,
          "heavy_weapon": false,
          "thrown_weapon": false,
          "damageDiceBase": "1d4+1d6",
          "parry_modifier": 0,
          "damage_original": "d4",
          "usable_in_melee": false,
          "counts_as_innate": false,
          "requires_2_hands": false,
          "damageDiceBasePlus": 0,
          "damageWithBrackets": "Str[d6]+d4",
          "add_strength_to_damage": true,
          "ap_vs_rigid_armor_only": 0
        }
      ],
      "bookID": 97,
      "activeProfile": 0
    },
    {
      "id": 1027,
      "uuid": "48627b63-4504-4b2a-25ff-38c423b36c4c",
      "name": "Lariat",
      "weight": 3,
      "range": "Melee",
      "damage": "Str",
      "equippedAs": "",
      "descriptionHTML": "<p><cite>Deadlands - The Weird West p.29</cite></p>",
      "damageWithBrackets": "Str[d6]",
      "rof": 0,
      "shots": 0,
      "ap": 0,
      "bookName": "Deadlands - The Weird West",
      "bookPublisher": "Pinnacle Entertainement Group",
      "bookPublished": "2020",
      "notes": "-1 Parry, Reach 2, Used to initiate a Test using the wielder’s Fighting skill. The target is Entangled with success, Bound on a raise.",
      "takenFrom": "Deadlands p.29",
      "thrown": false,
      "quantity": 1,
      "reach": 2,
      "innate": false,
      "damageDiceBase": "",
      "damageDiceBasePlus": 0,
      "equipped": false,
      "cost": 4,
      "costBuy": 4,
      "minStr": "d4",
      "profiles": [
        {
          "ap": 0,
          "rof": 0,
          "name": "",
          "notes": "-1 Parry, Reach 2, Used to initiate a Test using the wielder’s Fighting skill. The target is Entangled with success, Bound on a raise.",
          "range": "Melee",
          "reach": 2,
          "shots": 0,
          "damage": "Str",
          "toHitMod": 0,
          "vtt_only": false,
          "is_shield": false,
          "skillName": "Fighting",
          "melee_only": true,
          "skillValue": "d4-1",
          "currentShots": 0,
          "heavy_weapon": false,
          "thrown_weapon": false,
          "damageDiceBase": "1d6",
          "parry_modifier": -1,
          "damage_original": "-",
          "usable_in_melee": false,
          "counts_as_innate": false,
          "requires_2_hands": false,
          "damageDiceBasePlus": 0,
          "damageWithBrackets": "Str[d6]",
          "add_strength_to_damage": true,
          "ap_vs_rigid_armor_only": 0
        }
      ],
      "bookID": 97,
      "activeProfile": 0
    },
    {
      "id": 1065,
      "uuid": "c728b4b0-3e60-4af6-20b8-429976e60581",
      "name": "Winchester ‘73 (.44–40)",
      "weight": 10,
      "range": "24/48/96",
      "damage": "2d8-1",
      "equippedAs": "",
      "descriptionHTML": "<p><cite>Deadlands - The Weird West p.31</cite></p>",
      "damageWithBrackets": "2d8-1",
      "rof": 1,
      "shots": 15,
      "ap": 2,
      "bookName": "Deadlands - The Weird West",
      "bookPublisher": "Pinnacle Entertainement Group",
      "bookPublished": "2020",
      "notes": "",
      "takenFrom": "Deadlands p.31",
      "thrown": false,
      "quantity": 1,
      "reach": 0,
      "innate": false,
      "damageDiceBase": "2d8",
      "damageDiceBasePlus": -1,
      "equipped": false,
      "cost": 25,
      "costBuy": 25,
      "minStr": "d6",
      "profiles": [
        {
          "ap": 2,
          "rof": 1,
          "name": "",
          "notes": "",
          "range": "24/48/96",
          "reach": 0,
          "shots": 15,
          "damage": "2d8-1",
          "toHitMod": 0,
          "vtt_only": false,
          "is_shield": false,
          "skillName": "Shooting",
          "melee_only": false,
          "skillValue": "d8-1",
          "currentShots": 0,
          "heavy_weapon": false,
          "thrown_weapon": false,
          "damageDiceBase": "2d8",
          "parry_modifier": 0,
          "damage_original": "2d8-1",
          "usable_in_melee": false,
          "counts_as_innate": false,
          "requires_2_hands": false,
          "damageDiceBasePlus": -1,
          "damageWithBrackets": "2d8-1",
          "add_strength_to_damage": false,
          "ap_vs_rigid_armor_only": 0
        }
      ],
      "bookID": 97,
      "activeProfile": 0
    }
  ],
  "wildcard": true,
  "wounds": 0,
  "woundsBase": 3,
  "woundsMax": 3,
  "woundsOtherMod": 0,
  "woundsSizeMod": 0,
  "xp": 0,
  "otherAttacks": []
}